MANIFEST.in
README.md
requirements.txt
setup.py
tusuan/__init__.py
tusuan/file_function.py
tusuan/hello.py
tusuan/path_utils.py
tusuan/time_utils.py
tusuan.egg-info/PKG-INFO
tusuan.egg-info/SOURCES.txt
tusuan.egg-info/dependency_links.txt
tusuan.egg-info/requires.txt
tusuan.egg-info/top_level.txt
tusuan/datasets/__init__.py
tusuan/datasets/imagenet.py
tusuan/image_video_utils/__init__.py
tusuan/image_video_utils/croppers.py
tusuan/image_video_utils/display.py
tusuan/image_video_utils/image_visual_selector.py
tusuan/image_video_utils/readers.py
tusuan/image_video_utils/writers.py
tusuan/torch_utils/__init__.py