Metadata-Version: 2.1
Name: tusuan
Version: 0.0.9.2
Summary: useful functions.
Home-page: https://github.com/tusuan
Author: tusuan
Author-email: btk@qq.com
License: MIT
Keywords: tusuan
Platform: UNKNOWN
Classifier: Intended Audience :: Developers
Classifier: License :: OSI Approved :: MIT License
Classifier: Natural Language :: English
Classifier: Programming Language :: Python :: 3.8
Classifier: Programming Language :: Python :: 3.9
Classifier: Programming Language :: Python :: 3.10
Requires-Python: >=3.8.0
